better_exceptions_hook.pth
better_exceptions/__init__.py
better_exceptions/__main__.py
better_exceptions/color.py
better_exceptions/formatter.py
better_exceptions/highlighter.py
better_exceptions/log.py
better_exceptions/repl.py
better_exceptions_fork/__init__.py
better_exceptions_fork/__main__.py
better_exceptions_fork/color.py
better_exceptions_fork/formatter.py
better_exceptions_fork/highlighter.py
better_exceptions_fork/log.py
better_exceptions_fork/repl.py
better_exceptions_fork-0.2.1.post4.dist-info/DESCRIPTION.rst
better_exceptions_fork-0.2.1.post4.dist-info/METADATA
better_exceptions_fork-0.2.1.post4.dist-info/RECORD
better_exceptions_fork-0.2.1.post4.dist-info/WHEEL
better_exceptions_fork-0.2.1.post4.dist-info/metadata.json
better_exceptions_fork-0.2.1.post4.dist-info/top_level.txt
