Metadata-Version: 2.0
Name: better-exceptions-fork
Version: 0.2.1.post4
Summary: Pretty and helpful exceptions, automatically
Home-page: https://github.com/delgan/better-exceptions
Author: Delgan
Author-email: delgan.py@gmail.com
License: UNKNOWN
Download-URL: https://github.com/delgan/better-exceptions/archive/0.2.1.post4.tar.gz
Keywords: pretty,better,exceptions,exception,error,local,debug,debugging,locals
Platform: UNKNOWN
Requires-Dist: ansimarkup (>=1.3.0)
Requires-Dist: pygments (>=2.2.0)
Requires-Dist: colorama; sys_platform=="win32"
